[
  {
    "DB_NOTIF_ID": 14663395,
    "EMP_ID": 1,
    "TABLA_ID": 214,
    "CAMPO_ID": "ART_ID=19267,DEP_ID=1",
    "TRANSACTION_ID": 101892061,
    "TIPO_NOVEDAD": 1
  },
  {
    "DB_NOTIF_ID": 14663396,
    "EMP_ID": 1,
    "TABLA_ID": 214,
    "CAMPO_ID": "ART_ID=17475,DEP_ID=1",
    "TRANSACTION_ID": 101892061,
    "TIPO_NOVEDAD": 1
  },
  {
    "DB_NOTIF_ID": 14663397,
    "EMP_ID": 1,
    "TABLA_ID": 214,
    "CAMPO_ID": "ART_ID=17476,DEP_ID=1",
    "TRANSACTION_ID": 101892061,
    "TIPO_NOVEDAD": 1
  }
]
